plone.autoform-2.0.4-py3.13-nspkg.pth
plone/autoform/__init__.py
plone/autoform/autoform.rst
plone/autoform/base.py
plone/autoform/configure.zcml
plone/autoform/directives.py
plone/autoform/directives.txt
plone/autoform/form.py
plone/autoform/interfaces.py
plone/autoform/supermodel.py
plone/autoform/supermodel.txt
plone/autoform/testing.py
plone/autoform/utils.py
plone/autoform/view.py
plone/autoform/view.txt
plone/autoform/widgets.py
plone/autoform/tests/__init__.py
plone/autoform/tests/subform.txt
plone/autoform/tests/test_base.py
plone/autoform/tests/test_directives.py
plone/autoform/tests/test_doctests.py
plone/autoform/tests/test_supermodel_handler.py
plone/autoform/tests/test_utils.py
plone/autoform/tests/test_widgets.py
plone_autoform-2.0.4.dist-info/METADATA
plone_autoform-2.0.4.dist-info/WHEEL
plone_autoform-2.0.4.dist-info/namespace_packages.txt
plone_autoform-2.0.4.dist-info/top_level.txt
plone_autoform-2.0.4.dist-info/RECORD
