Metadata-Version: 2.4
Name: plone.autoform
Version: 2.0.4
Summary: Tools to construct z3c.form forms
Home-page: http://github.com/plone/plone.autoform
Author: Martin Aspeli
Author-email: optilude@gmail.com
License: LGPL
Keywords: plone form z3c.form
Classifier: Development Status :: 5 - Production/Stable
Classifier: Framework :: Plone
Classifier: Framework :: Plone :: Core
Classifier: Framework :: Plone :: 6.0
Classifier: License :: OSI Approved :: GNU Library or Lesser General Public License (LGPL)
Classifier: Programming Language :: Python
Classifier: Programming Language :: Python :: 3.8
Classifier: Programming Language :: Python :: 3.9
Classifier: Programming Language :: Python :: 3.10
Classifier: Programming Language :: Python :: 3.11
Classifier: Topic :: Software Development :: Libraries :: Python Modules
Requires-Python: >=3.8
Requires-Dist: lxml
Requires-Dist: setuptools
Requires-Dist: plone.supermodel>=1.3
Requires-Dist: plone.z3cform>=2.0.0
Requires-Dist: z3c.form
Requires-Dist: Zope
Provides-Extra: test
Requires-Dist: plone.testing; extra == "test"
Dynamic: author
Dynamic: author-email
Dynamic: classifier
Dynamic: description
Dynamic: description-content-type
Dynamic: home-page
Dynamic: keywords
Dynamic: license
Dynamic: provides-extra
Dynamic: requires-dist
Dynamic: requires-python
Dynamic: summary
